LICENSE
setup.cfg
setup.py
toolboxlb/__init__.py
toolboxlb/client.py
toolboxlb.egg-info/PKG-INFO
toolboxlb.egg-info/SOURCES.txt
toolboxlb.egg-info/dependency_links.txt
toolboxlb.egg-info/not-zip-safe
toolboxlb.egg-info/top_level.txt