Metadata-Version: 2.1
Name: toolboxlb
Version: 1.0
Summary: it`s a toolbox, this is multitool-library 
Author: xlebl
Author-email: logepist.top@gmail.com
License-File: LICENSE
